vllm_mlx/__init__.py
vllm_mlx/attention.py
vllm_mlx/benchmark.py
vllm_mlx/cli.py
vllm_mlx/engine_core.py
vllm_mlx/gradio_app.py
vllm_mlx/gradio_text_app.py
vllm_mlx/memory_cache.py
vllm_mlx/mllm_batch_generator.py
vllm_mlx/mllm_cache.py
vllm_mlx/mllm_scheduler.py
vllm_mlx/model_registry.py
vllm_mlx/model_runner.py
vllm_mlx/multimodal_processor.py
vllm_mlx/optimizations.py
vllm_mlx/output_collector.py
vllm_mlx/paged_cache.py
vllm_mlx/platform.py
vllm_mlx/plugin.py
vllm_mlx/prefix_cache.py
vllm_mlx/request.py
vllm_mlx/scheduler.py
vllm_mlx/server.py
vllm_mlx/vision_embedding_cache.py
vllm_mlx/worker.py
vllm_mlx/api/__init__.py
vllm_mlx/api/models.py
vllm_mlx/api/tool_calling.py
vllm_mlx/api/utils.py
vllm_mlx/audio/__init__.py
vllm_mlx/audio/processor.py
vllm_mlx/audio/stt.py
vllm_mlx/audio/tts.py
vllm_mlx/engine/__init__.py
vllm_mlx/engine/base.py
vllm_mlx/engine/batched.py
vllm_mlx/engine/simple.py
vllm_mlx/mcp/__init__.py
vllm_mlx/mcp/client.py
vllm_mlx/mcp/config.py
vllm_mlx/mcp/executor.py
vllm_mlx/mcp/manager.py
vllm_mlx/mcp/security.py
vllm_mlx/mcp/tools.py
vllm_mlx/mcp/types.py
vllm_mlx/models/__init__.py
vllm_mlx/models/llm.py
vllm_mlx/models/mllm.py
vllm_mlx/utils/__init__.py
vllm_mlx/utils/chat_templates.py
vllm_mlx/utils/mamba_cache.py
vllm_mlx/utils/tokenizer.py
vllm_mlx-0.2.5.dist-info/METADATA
vllm_mlx-0.2.5.dist-info/WHEEL
vllm_mlx-0.2.5.dist-info/entry_points.txt
vllm_mlx-0.2.5.dist-info/top_level.txt
vllm_mlx-0.2.5.dist-info/RECORD
