Metadata-Version: 2.4
Name: vllm-mlx
Version: 0.2.5
Summary: vLLM-like inference for Apple Silicon - GPU-accelerated Text, Image, Video & Audio on Mac
Author: vllm-mlx contributors
License: Apache-2.0
Project-URL: Homepage, https://github.com/vllm-mlx/vllm-mlx
Project-URL: Documentation, https://github.com/vllm-mlx/vllm-mlx#readme
Project-URL: Repository, https://github.com/vllm-mlx/vllm-mlx
Keywords: llm,mlx,apple-silicon,vllm,inference,transformers
Classifier: Development Status :: 3 - Alpha
Classifier: Intended Audience :: Developers
Classifier: Intended Audience :: Science/Research
Classifier: License :: OSI Approved :: Apache Software License
Classifier: Operating System :: MacOS
Classifier: Programming Language :: Python :: 3
Classifier: Programming Language :: Python :: 3.10
Classifier: Programming Language :: Python :: 3.11
Classifier: Programming Language :: Python :: 3.12
Classifier: Programming Language :: Python :: 3.13
Classifier: Topic :: Scientific/Engineering :: Artificial Intelligence
Requires-Python: >=3.10
Requires-Dist: mlx>=0.29.0
Requires-Dist: mlx-lm>=0.30.2
Requires-Dist: mlx-vlm>=0.1.0
Requires-Dist: transformers<=5.0.0rc1,>=4.40.0
Requires-Dist: tokenizers>=0.19.0
Requires-Dist: huggingface-hub>=0.23.0
Requires-Dist: numpy>=1.24.0
Requires-Dist: pillow>=10.0.0
Requires-Dist: tqdm>=4.66.0
Requires-Dist: pyyaml>=6.0
Requires-Dist: gradio>=4.0.0
Requires-Dist: requests>=2.28.0
Requires-Dist: tabulate>=0.9.0
Requires-Dist: opencv-python>=4.8.0
Requires-Dist: torchvision>=0.18.0
Requires-Dist: psutil>=5.9.0
Requires-Dist: fastapi>=0.100.0
Requires-Dist: uvicorn>=0.23.0
Requires-Dist: mcp>=1.0.0
Requires-Dist: jsonschema>=4.0.0
Provides-Extra: dev
Requires-Dist: pytest>=7.0.0; extra == "dev"
Requires-Dist: pytest-asyncio>=0.21.0; extra == "dev"
Requires-Dist: black>=23.0.0; extra == "dev"
Requires-Dist: ruff>=0.1.0; extra == "dev"
Requires-Dist: mypy>=1.0.0; extra == "dev"
Provides-Extra: vllm
Requires-Dist: vllm>=0.4.0; extra == "vllm"
Provides-Extra: vision
Requires-Dist: torch>=2.3.0; extra == "vision"
Requires-Dist: torchvision>=0.18.0; extra == "vision"
Provides-Extra: audio
Requires-Dist: mlx-audio>=0.2.9; extra == "audio"
Requires-Dist: sounddevice>=0.4.0; extra == "audio"
Requires-Dist: soundfile>=0.12.0; extra == "audio"
Requires-Dist: scipy>=1.10.0; extra == "audio"
Requires-Dist: numba>=0.57.0; extra == "audio"
Requires-Dist: tiktoken>=0.5.0; extra == "audio"
Requires-Dist: misaki[ja,zh]>=0.5.0; extra == "audio"
Requires-Dist: spacy>=3.7.0; extra == "audio"
Requires-Dist: num2words>=0.5.0; extra == "audio"
Requires-Dist: loguru>=0.7.0; extra == "audio"
Requires-Dist: phonemizer>=3.2.0; extra == "audio"
Requires-Dist: ordered_set>=4.1.0; extra == "audio"
Requires-Dist: cn2an>=0.5.0; extra == "audio"
Requires-Dist: fugashi>=1.3.0; extra == "audio"
Requires-Dist: unidic-lite>=1.0.0; extra == "audio"
Requires-Dist: jieba>=0.42.0; extra == "audio"
